Metadata-Version: 2.1
Name: newguy103-syncserver
Version: 1.3.0
Summary: newguy103-syncserver simplifies file synchronization using Flask-based server and client modules.
Author: NewGuy103
Author-email: userchouenthusiast@gmail.com
Classifier: Programming Language :: Python :: 3.11
Classifier: Programming Language :: Python :: 3.12
Requires-Dist: cryptography
Requires-Dist: requests
Requires-Dist: flask
Requires-Dist: argon2-cffi
Requires-Dist: msgpack
Requires-Dist: pyqt5
